french_republican_calendar.py
frenchrepublicancalendar-1.0.1.dist-info/licenses/LICENSE
frenchrepublicancalendar-1.0.1.dist-info/METADATA
frenchrepublicancalendar-1.0.1.dist-info/WHEEL
frenchrepublicancalendar-1.0.1.dist-info/top_level.txt
frenchrepublicancalendar-1.0.1.dist-info/RECORD
