Metadata-Version: 2.4
Name: FrenchRepublicanCalendar
Version: 1.0.1
Summary: French Republican Calendar convertor to Gregorian Date Objects.
Author-email: Nicolas Flandrois <contacts@flandrois.com>
Maintainer-email: Nicolas Flandrois <nicolas.dev@flandrois.com>
License:                     GNU GENERAL PUBLIC LICENSE
Project-URL: Homepage, https://github.com/NicolasFlandrois/French-Republican-Calendar-Python-Package
Project-URL: GitHub, https://github.com/NicolasFlandrois/French-Republican-Calendar-Python-Package
Keywords: french,republican,calendar,datetime,convertor
Classifier: Programming Language :: Python :: 3
Classifier: License :: OSI Approved :: GNU General Public License v3 (GPLv3)
Classifier: Operating System :: OS Independent
Requires-Python: >=3.14
License-File: LICENSE
Dynamic: license-file
